context_predeployed/__init__.py
context_predeployed/address.py
context_predeployed/context_generator.py
context_predeployed/artifacts/Context.json
context_predeployed/artifacts/Context.meta.json
test/__init__.py
test/test_context_generator.py
test/tools/__init__.py
test/tools/test_predeployed.py
test/tools/test_solidity_project.py
context_predeployed-1.0.0.dev4.dist-info/METADATA
context_predeployed-1.0.0.dev4.dist-info/WHEEL
context_predeployed-1.0.0.dev4.dist-info/top_level.txt
context_predeployed-1.0.0.dev4.dist-info/RECORD
